anymail/__init__.py
anymail/_version.py
anymail/apps.py
anymail/checks.py
anymail/exceptions.py
anymail/inbound.py
anymail/message.py
anymail/signals.py
anymail/urls.py
anymail/utils.py
anymail/backends/__init__.py
anymail/backends/amazon_ses.py
anymail/backends/amazon_sesv2.py
anymail/backends/base.py
anymail/backends/base_requests.py
anymail/backends/console.py
anymail/backends/mailersend.py
anymail/backends/mailgun.py
anymail/backends/mailjet.py
anymail/backends/mandrill.py
anymail/backends/postal.py
anymail/backends/postmark.py
anymail/backends/sendgrid.py
anymail/backends/sendinblue.py
anymail/backends/sparkpost.py
anymail/backends/test.py
anymail/webhooks/__init__.py
anymail/webhooks/amazon_ses.py
anymail/webhooks/base.py
anymail/webhooks/mailersend.py
anymail/webhooks/mailgun.py
anymail/webhooks/mailjet.py
anymail/webhooks/mandrill.py
anymail/webhooks/postal.py
anymail/webhooks/postmark.py
anymail/webhooks/sendgrid.py
anymail/webhooks/sendinblue.py
anymail/webhooks/sparkpost.py
django_anymail-9.2.dist-info/LICENSE
django_anymail-9.2.dist-info/METADATA
django_anymail-9.2.dist-info/WHEEL
django_anymail-9.2.dist-info/top_level.txt
django_anymail-9.2.dist-info/RECORD
