Metadata-Version: 2.1
Name: django-anymail
Version: 9.2
Summary: Django email backends and webhooks for Amazon SES, MailerSend, Mailgun, Mailjet, Mandrill, Postal, Postmark, SendGrid, SendinBlue, and SparkPost
Home-page: https://github.com/anymail/django-anymail
Author: Mike Edmunds and Anymail contributors
Author-email: medmunds@gmail.com
License: BSD License
Project-URL: Documentation, https://anymail.dev/en/v9.2/
Project-URL: Source, https://github.com/anymail/django-anymail
Project-URL: Changelog, https://anymail.dev/en/v9.2/changelog/
Project-URL: Tracker, https://github.com/anymail/django-anymail/issues
Keywords: Django,email,email backend,ESP,transactional mail,Amazon SES,MailerSend,Mailgun,Mailjet,Mandrill,Postal,Postmark,SendGrid,SendinBlue,SparkPost
Classifier: Development Status :: 5 - Production/Stable
Classifier: Programming Language :: Python
Classifier: Programming Language :: Python :: Implementation :: PyPy
Classifier: Programming Language :: Python :: Implementation :: CPython
Classifier: Programming Language :: Python :: 3
Classifier: Programming Language :: Python :: 3.6
Classifier: Programming Language :: Python :: 3.7
Classifier: Programming Language :: Python :: 3.8
Classifier: Programming Language :: Python :: 3.9
Classifier: Programming Language :: Python :: 3.10
Classifier: Programming Language :: Python :: 3.11
Classifier: License :: OSI Approved :: BSD License
Classifier: Topic :: Communications :: Email
Classifier: Topic :: Software Development :: Libraries :: Python Modules
Classifier: Intended Audience :: Developers
Classifier: Framework :: Django
Classifier: Framework :: Django :: 3.0
Classifier: Framework :: Django :: 3.1
Classifier: Framework :: Django :: 3.2
Classifier: Framework :: Django :: 4.0
Classifier: Framework :: Django :: 4.1
Classifier: Framework :: Django :: 4.2
Classifier: Environment :: Web Environment
Requires-Python: >=3.6
Provides-Extra: amazon_ses
Provides-Extra: mailersend
Provides-Extra: mailgun
Provides-Extra: mailjet
Provides-Extra: mandrill
Provides-Extra: postmark
Provides-Extra: sendgrid
Provides-Extra: sendinblue
Provides-Extra: sparkpost
Provides-Extra: postal
Provides-Extra: dev
Provides-Extra: test
License-File: LICENSE
